redacty/__init__.py
redacty/__main__.py
redacty/redacty.py
redacty-2.0.1.dist-info/LICENSE
redacty-2.0.1.dist-info/METADATA
redacty-2.0.1.dist-info/WHEEL
redacty-2.0.1.dist-info/entry_points.txt
redacty-2.0.1.dist-info/RECORD
