Metadata-Version: 2.1
Name: redacty
Version: 2.0.1
Summary: This is a CLI tool that redacts emails from bodies of text in a PostgreSQL database.
Home-page: https://github.com/wet-bulb/redacty
Author: angelica robitaille
Author-email: ng3lica@gmail.com
Requires-Python: >=3.8,<4.0
Classifier: Programming Language :: Python :: 3
Classifier: Programming Language :: Python :: 3.8
Classifier: Programming Language :: Python :: 3.9
Classifier: Programming Language :: Python :: 3.10
Classifier: Programming Language :: Python :: 3.11
Requires-Dist: psycopg2-binary (>=2.9.6,<3.0.0)
Project-URL: Documentation, https://wet-bulb.github.io/redacty/
Project-URL: Repository, https://github.com/wet-bulb/redacty
